setup.py
src/fc_simesh/__init__.py
src/fc_simesh/demos.py
src/fc_simesh/init.py
src/fc_simesh/siMesh.py
src/fc_simesh/siMeshElt.py
src/fc_simesh/sys.py
src/fc_simesh.egg-info/PKG-INFO
src/fc_simesh.egg-info/SOURCES.txt
src/fc_simesh.egg-info/dependency_links.txt
src/fc_simesh.egg-info/requires.txt
src/fc_simesh.egg-info/top_level.txt
src/fc_simesh/geodir/2d/options01_data.geo
src/fc_simesh/geodir/2d/shape_functions.geo
src/fc_simesh/geodir/3d/cube6.geo
src/fc_simesh/geodir/3d/cylinder3dom.geo
src/fc_simesh/geodir/3d/cylinder3holes.geo
src/fc_simesh/geodir/3d/cylinderkey.geo